pyice/__init__.py
pyice/core.py
pyice/core_v4.py
pyice/web.py
pyice/web_async.py
pyice/web_async_v4.py
pyice/web_v4.py
pyice-0.2.1.dist-info/DESCRIPTION.rst
pyice-0.2.1.dist-info/METADATA
pyice-0.2.1.dist-info/RECORD
pyice-0.2.1.dist-info/WHEEL
pyice-0.2.1.dist-info/metadata.json
pyice-0.2.1.dist-info/top_level.txt
