Metadata-Version: 2.0
Name: pyice
Version: 0.2.1
Summary: High performance Web server framework based on Ice Core
Home-page: https://github.com/losfair/ice-python
Author: Heyang Zhou
Author-email: i@ifxor.com
License: MIT
Keywords: web framework http server performance ice core
Platform: UNKNOWN
Classifier: Development Status :: 3 - Alpha
Classifier: License :: OSI Approved :: MIT License
Classifier: Programming Language :: Python :: 3
Classifier: Programming Language :: Python :: 3.5
Classifier: Programming Language :: Python :: 3.6
Requires-Python: >=3
Requires-Dist: cffi
